maxx/__init__.py
maxx/collection.py
maxx/enums.py
maxx/exceptions.py
maxx/expressions.py
maxx/logger.py
maxx/matlab_builtins.json
maxx/mixins.py
maxx/objects.py
maxx/py.typed
maxx/treesitter.py
maxx-0.6.3.dist-info/METADATA
maxx-0.6.3.dist-info/WHEEL
maxx-0.6.3.dist-info/licenses/LICENSE
maxx-0.6.3.dist-info/RECORD
